repo_kit/__init__.py
repo_kit/applier.py
repo_kit/badges.py
repo_kit/cli.py
repo_kit/git_utils.py
repo_kit/models.py
repo_kit/scanner.py
repo_kit/score_svg.py
repo_kit/templates_content.py
repo_kit-0.1.0.dist-info/METADATA
repo_kit-0.1.0.dist-info/WHEEL
repo_kit-0.1.0.dist-info/entry_points.txt
repo_kit-0.1.0.dist-info/licenses/LICENSE
repo_kit-0.1.0.dist-info/RECORD
