Metadata-Version: 2.4
Name: repo-kit
Version: 0.1.0
Summary: Repo health check + one-command professional open-source kit.
Author: lee Zi
License: MIT
License-File: LICENSE
Keywords: badge,cli,github,opensource,repository,template
Classifier: Development Status :: 3 - Alpha
Classifier: Environment :: Console
Classifier: License :: OSI Approved :: MIT License
Classifier: Programming Language :: Python :: 3
Classifier: Programming Language :: Python :: 3 :: Only
Classifier: Topic :: Software Development :: Quality Assurance
Classifier: Topic :: Software Development :: Version Control :: Git
Requires-Python: >=3.10
Requires-Dist: rich>=13.7.1
Requires-Dist: typer>=0.12.3
Provides-Extra: dev
Requires-Dist: pytest>=8.0.0; extra == 'dev'
